streamparse/__init__.py
streamparse/bolt.py
streamparse/component.py
streamparse/run.py
streamparse/spout.py
streamparse/thrift.py
streamparse/util.py
streamparse/version.py
streamparse/bootstrap/__init__.py
streamparse/bootstrap/project/config.jinja2.json
streamparse/bootstrap/project/fabfile.py
streamparse/bootstrap/project/gitignore
streamparse/bootstrap/project/project.jinja2.clj
streamparse/bootstrap/project/src/bolts/__init__.py
streamparse/bootstrap/project/src/bolts/wordcount.py
streamparse/bootstrap/project/src/spouts/__init__.py
streamparse/bootstrap/project/src/spouts/words.py
streamparse/bootstrap/project/topologies/wordcount.py
streamparse/bootstrap/project/virtualenvs/wordcount.txt
streamparse/cli/__init__.py
streamparse/cli/common.py
streamparse/cli/jar.py
streamparse/cli/kill.py
streamparse/cli/list.py
streamparse/cli/quickstart.py
streamparse/cli/remove_logs.py
streamparse/cli/run.py
streamparse/cli/slot_usage.py
streamparse/cli/sparse.py
streamparse/cli/stats.py
streamparse/cli/submit.py
streamparse/cli/tail.py
streamparse/cli/update_virtualenv.py
streamparse/cli/visualize.py
streamparse/cli/worker_uptime.py
streamparse/dsl/__init__.py
streamparse/dsl/bolt.py
streamparse/dsl/component.py
streamparse/dsl/spout.py
streamparse/dsl/stream.py
streamparse/dsl/topology.py
streamparse/dsl/util.py
streamparse/storm/__init__.py
streamparse/storm/bolt.py
streamparse/storm/component.py
streamparse/storm/spout.py
test/__init__.py
test/streamparse/__init__.py
test/streamparse/test_dsl.py
test/streamparse/test_streamparse_run.py
test/streamparse/cli/__init__.py
test/streamparse/cli/test_attach.py
test/streamparse/cli/test_common.py
test/streamparse/cli/test_jar.py
test/streamparse/cli/test_kill.py
test/streamparse/cli/test_list.py
test/streamparse/cli/test_logs.py
test/streamparse/cli/test_quickstart.py
test/streamparse/cli/test_remove_logs.py
test/streamparse/cli/test_run.py
test/streamparse/cli/test_sparse.py
test/streamparse/cli/test_stats.py
streamparse-5.0.1.dist-info/LICENSE
streamparse-5.0.1.dist-info/METADATA
streamparse-5.0.1.dist-info/WHEEL
streamparse-5.0.1.dist-info/entry_points.txt
streamparse-5.0.1.dist-info/top_level.txt
streamparse-5.0.1.dist-info/RECORD
