Metadata-Version: 2.1
Name: streamparse
Version: 5.0.1
Summary: streamparse lets you run Python code against real-time streams of data. Integrates with Apache Storm.
Home-page: https://github.com/Parsely/streamparse
Author: Parsely, Inc.
Author-email: hello@parsely.com
License: Apache License 2.0
Classifier: License :: OSI Approved :: Apache Software License
Classifier: Programming Language :: Python
Classifier: Programming Language :: Python :: 3
Classifier: Programming Language :: Python :: 3.6
Classifier: Programming Language :: Python :: 3.7
Classifier: Programming Language :: Python :: 3.8
Classifier: Programming Language :: Python :: 3.9
Classifier: Programming Language :: Python :: Implementation :: CPython
Classifier: Programming Language :: Python :: Implementation :: PyPy
License-File: LICENSE
Requires-Dist: cython
Requires-Dist: jinja2
Requires-Dist: Fabric39
Requires-Dist: pystorm >=3.1.1
Requires-Dist: requests
Requires-Dist: ruamel.yaml
Requires-Dist: setuptools
Requires-Dist: simplejson
Requires-Dist: texttable
Requires-Dist: thriftpy2
Provides-Extra: all
Requires-Dist: cython ; extra == 'all'
Requires-Dist: jinja2 ; extra == 'all'
Requires-Dist: Fabric39 ; extra == 'all'
Requires-Dist: pystorm >=3.1.1 ; extra == 'all'
Requires-Dist: requests ; extra == 'all'
Requires-Dist: ruamel.yaml ; extra == 'all'
Requires-Dist: setuptools ; extra == 'all'
Requires-Dist: simplejson ; extra == 'all'
Requires-Dist: texttable ; extra == 'all'
Requires-Dist: thriftpy2 ; extra == 'all'
Requires-Dist: graphviz ; extra == 'all'
Requires-Dist: pytest ; extra == 'all'
Provides-Extra: docs
Requires-Dist: sphinx ; extra == 'docs'
Requires-Dist: graphviz ; extra == 'docs'
Requires-Dist: pytest ; extra == 'docs'
Provides-Extra: test
Requires-Dist: graphviz ; extra == 'test'
Requires-Dist: pytest ; extra == 'test'
